dynamodb_encryption_sdk/__init__.py
dynamodb_encryption_sdk/compatability.py
dynamodb_encryption_sdk/exceptions.py
dynamodb_encryption_sdk/identifiers.py
dynamodb_encryption_sdk/structures.py
dynamodb_encryption_sdk/transform.py
dynamodb_encryption_sdk/delegated_keys/__init__.py
dynamodb_encryption_sdk/delegated_keys/jce.py
dynamodb_encryption_sdk/encrypted/__init__.py
dynamodb_encryption_sdk/encrypted/client.py
dynamodb_encryption_sdk/encrypted/item.py
dynamodb_encryption_sdk/encrypted/resource.py
dynamodb_encryption_sdk/encrypted/table.py
dynamodb_encryption_sdk/internal/__init__.py
dynamodb_encryption_sdk/internal/dynamodb_types.py
dynamodb_encryption_sdk/internal/identifiers.py
dynamodb_encryption_sdk/internal/str_ops.py
dynamodb_encryption_sdk/internal/utils.py
dynamodb_encryption_sdk/internal/validators.py
dynamodb_encryption_sdk/internal/crypto/__init__.py
dynamodb_encryption_sdk/internal/crypto/authentication.py
dynamodb_encryption_sdk/internal/crypto/encryption.py
dynamodb_encryption_sdk/internal/crypto/jce_bridge/__init__.py
dynamodb_encryption_sdk/internal/crypto/jce_bridge/authentication.py
dynamodb_encryption_sdk/internal/crypto/jce_bridge/encryption.py
dynamodb_encryption_sdk/internal/crypto/jce_bridge/primitives.py
dynamodb_encryption_sdk/internal/formatting/__init__.py
dynamodb_encryption_sdk/internal/formatting/material_description.py
dynamodb_encryption_sdk/internal/formatting/deserialize/__init__.py
dynamodb_encryption_sdk/internal/formatting/deserialize/attribute.py
dynamodb_encryption_sdk/internal/formatting/serialize/__init__.py
dynamodb_encryption_sdk/internal/formatting/serialize/attribute.py
dynamodb_encryption_sdk/material_providers/__init__.py
dynamodb_encryption_sdk/material_providers/aws_kms.py
dynamodb_encryption_sdk/material_providers/most_recent.py
dynamodb_encryption_sdk/material_providers/static.py
dynamodb_encryption_sdk/material_providers/wrapped.py
dynamodb_encryption_sdk/material_providers/store/__init__.py
dynamodb_encryption_sdk-3.3.0.dist-info/LICENSE
dynamodb_encryption_sdk-3.3.0.dist-info/METADATA
dynamodb_encryption_sdk-3.3.0.dist-info/WHEEL
dynamodb_encryption_sdk-3.3.0.dist-info/top_level.txt
dynamodb_encryption_sdk-3.3.0.dist-info/RECORD
