Metadata-Version: 2.1
Name: dynamodb-encryption-sdk
Version: 3.3.0
Summary: DynamoDB Encryption Client for Python
Home-page: https://github.com/aws/aws-dynamodb-encryption-python
Author: Amazon Web Services
Author-email: aws-cryptools@amazon.com
Maintainer: Amazon Web Services
License: Apache License 2.0
Keywords: dynamodb-encryption-sdk aws kms encryption dynamodb
Classifier: Development Status :: 5 - Production/Stable
Classifier: Intended Audience :: Developers
Classifier: Natural Language :: English
Classifier: License :: OSI Approved :: Apache Software License
Classifier: Programming Language :: Python
Classifier: Programming Language :: Python :: 3
Classifier: Programming Language :: Python :: 3.8
Classifier: Programming Language :: Python :: 3.9
Classifier: Programming Language :: Python :: 3.10
Classifier: Programming Language :: Python :: 3.11
Classifier: Programming Language :: Python :: 3.12
Classifier: Programming Language :: Python :: Implementation :: CPython
Classifier: Topic :: Security
Classifier: Topic :: Security :: Cryptography
License-File: LICENSE
Requires-Dist: boto3 (>=1.10.0)
Requires-Dist: cryptography (>=3.4.6)
Requires-Dist: attrs (>=17.4.0)
